{
    "opts": {
        "template": "templates/default",
        "encoding": "utf8",
        "destination": "doc/",
        "recurse": true
    },
    "recurseDepth": 10,
    "sourceType": "module",
    "source": {
        "include": [
            "src/"
        ],
        "exclude": [],
        "includePattern": ".+\\.js(doc|x)?$",
        "excludePattern": "(^|\\/|\\\\)_"
    },
    "tags": {
        "allowUnknownTags": false,
        "dictionaries": [
            "jsdoc",
            "closure"
        ]
    },
    "templates": {
        "cleverLinks": false,
        "monospaceLinks": false
    }
}